__init__.py
fast_serial.py
scripts.py
settings.py
lib/__init__.py
lib/actions.py
lib/connect.py
lib/dialogs.py
lib/expect.py
lib/filters.py
lib/git_version.py
lib/history.py
lib/project.py
lib/serial_port.py
lib/set.py
lib/text.py
ui/__init__.py
ui/make_uis.py
ui/run_action.py
ui/ui_action_dialog.py
ui/ui_application.py
ui/ui_filter_dialog.py
ui/ui_run_dialog.py
fast_serial-1.1.dist-info/LICENSE
fast_serial-1.1.dist-info/METADATA
fast_serial-1.1.dist-info/WHEEL
fast_serial-1.1.dist-info/top_level.txt
fast_serial-1.1.dist-info/RECORD
