Metadata-Version: 2.1
Name: fast-serial
Version: 1.1
Summary: Fast serial terminal with macros and filtering
Author-email: Mike Wilson <mail4mikew@gmail.com>
Project-URL: Homepage, https://github.com/mj8w/fast_serial
Project-URL: Bug Tracker, https://github.com/mj8w/fast_serial/issues
Classifier: Programming Language :: Python :: 3
Classifier: License :: OSI Approved :: GNU General Public License v2 (GPLv2)
Classifier: Operating System :: OS Independent
Requires-Python: >=3.8
License-File: LICENSE
Requires-Dist: pyserial >=3.5
Requires-Dist: pyqt5 >=5.15
